MANIFEST.in
README.txt
setup.py
docs/HISTORY.txt
docs/INSTALL.txt
docs/LICENSE.GPL
docs/LICENSE.txt
quintagroup/__init__.py
quintagroup.theme.lite.egg-info/PKG-INFO
quintagroup.theme.lite.egg-info/SOURCES.txt
quintagroup.theme.lite.egg-info/dependency_links.txt
quintagroup.theme.lite.egg-info/entry_points.txt
quintagroup.theme.lite.egg-info/namespace_packages.txt
quintagroup.theme.lite.egg-info/not-zip-safe
quintagroup.theme.lite.egg-info/requires.txt
quintagroup.theme.lite.egg-info/top_level.txt
quintagroup/theme/__init__.py
quintagroup/theme/lite/README.txt
quintagroup/theme/lite/__init__.py
quintagroup/theme/lite/configure.zcml
quintagroup/theme/lite/profiles/default/metadata.xml
quintagroup/theme/lite/profiles/default/theme.xml
quintagroup/theme/lite/profiles/default/tinymce.xml
quintagroup/theme/lite/static/extra.html
quintagroup/theme/lite/static/index.html
quintagroup/theme/lite/static/manifest.cfg
quintagroup/theme/lite/static/rules.xml
quintagroup/theme/lite/static/css/IEFixes.css
quintagroup/theme/lite/static/css/lite.css
quintagroup/theme/lite/static/css/splash.css
quintagroup/theme/lite/static/css/splash1.css
quintagroup/theme/lite/static/css/splash2.css
quintagroup/theme/lite/static/images/album.png
quintagroup/theme/lite/static/images/bg-column-left.gif
quintagroup/theme/lite/static/images/bg-columns.gif
quintagroup/theme/lite/static/images/favicon.ico
quintagroup/theme/lite/static/images/icons-sprite.png
quintagroup/theme/lite/static/images/lite_sprite.png
quintagroup/theme/lite/static/images/logoLite.png
quintagroup/theme/lite/static/images/pb_close.png
quintagroup/theme/lite/static/images/top_images/.objects
quintagroup/theme/lite/static/images/top_images/bg_top1.jpg
quintagroup/theme/lite/static/images/top_images/bg_top2.jpg
quintagroup/theme/lite/static/images/top_images/bg_top3.jpg
quintagroup/theme/lite/static/js/splash.js