Metadata-Version: 1.0
Name: quintagroup.theme.lite
Version: 6.0.4
Summary: Free Diazo Theme for Plone 4.1
Home-page: http://skins.quintagroup.com/lite
Author: Quintagroup
Author-email: skins@quintagroup.com
License: GPL
Keywords: web zope plone theme quintagroup
Platform: UNKNOWN
Classifier: Framework :: Plone
Classifier: Intended Audience :: Developers
Classifier: Topic :: Software Development :: Libraries :: Python Modules
Classifier: License :: OSI Approved :: GNU General Public License (GPL)
